artsemLib/__about__.py
artsemLib/__init__.py
artsemLib/persistence.py
artsemLib/probes.py
artsemlib-0.0.32.dist-info/METADATA
artsemlib-0.0.32.dist-info/WHEEL
artsemlib-0.0.32.dist-info/licenses/LICENSE.txt
artsemlib-0.0.32.dist-info/RECORD
